persian_sentiment_analyzer/__init__.py
persian_sentiment_analyzer/model.py
persian_sentiment_analyzer/preprocessor.py
persian_sentiment_analyzer/utils.py
persian_sentiment_analyzer-0.1.9.dist-info/LICENSE.txt
persian_sentiment_analyzer-0.1.9.dist-info/METADATA
persian_sentiment_analyzer-0.1.9.dist-info/WHEEL
persian_sentiment_analyzer-0.1.9.dist-info/top_level.txt
persian_sentiment_analyzer-0.1.9.dist-info/RECORD
