Metadata-Version: 2.2
Name: persian_sentiment_analyzer
Version: 0.1.9
Summary: Persian Sentiment Analysis Library
Home-page: https://github.com/RezaGooner/Sentiment-Survey-Analyzer/
Author: RezaGooner
Author-email: RezaAsadiProgrammer@Gmail.com
Classifier: Programming Language :: Python :: 3
Classifier: License :: OSI Approved :: MIT License
Requires-Python: >=3.6
License-File: LICENSE.txt
Requires-Dist: hazm>=0.7.0
Requires-Dist: gensim>=4.0.0
Requires-Dist: scikit-learn>=1.0.0
Requires-Dist: numpy>=1.20.0
Dynamic: author
Dynamic: author-email
Dynamic: classifier
Dynamic: description
Dynamic: description-content-type
Dynamic: home-page
Dynamic: requires-dist
Dynamic: requires-python
Dynamic: summary
